deipy/__init__.py
deipy-1.0.dist-info/METADATA
deipy-1.0.dist-info/WHEEL
deipy-1.0.dist-info/top_level.txt
deipy-1.0.dist-info/RECORD
